{
  "parent": "minecraft:recipes/root",
  "criteria": {
    "has_kaolinite_bricks": {
      "conditions": {
        "items": [
          {
            "items": [
              "rankine:kaolinite_bricks"
            ]
          }
        ]
      },
      "trigger": "minecraft:inventory_changed"
    },
    "has_the_recipe": {
      "conditions": {
        "recipe": "rankine:kaolinite_bricks_slab_from_kaolinite_bricks_stonecutting"
      },
      "trigger": "minecraft:recipe_unlocked"
    }
  },
  "requirements": [
    [
      "has_kaolinite_bricks",
      "has_the_recipe"
    ]
  ],
  "rewards": {
    "recipes": [
      "rankine:kaolinite_bricks_slab_from_kaolinite_bricks_stonecutting"
    ]
  }
}