{
  "parent": "minecraft:recipes/root",
  "criteria": {
    "has_ingredient": {
      "conditions": {
        "items": [
          {
            "items": [
              "rankine:mariposite_bricks"
            ]
          }
        ]
      },
      "trigger": "minecraft:inventory_changed"
    },
    "has_the_recipe": {
      "conditions": {
        "recipe": "rankine:mariposite_brick_button_from_mariposite_bricks_stonecutting"
      },
      "trigger": "minecraft:recipe_unlocked"
    }
  },
  "requirements": [
    [
      "has_ingredient",
      "has_the_recipe"
    ]
  ],
  "rewards": {
    "recipes": [
      "rankine:mariposite_brick_button_from_mariposite_bricks_stonecutting"
    ]
  }
}