{
	"credit": "Made with Blockbench",
	"parent": "block/block",
	"textures": {
		"0": "rankine:block/cinnabar_polypore",
		"particle": "rankine:block/cinnabar_polypore"
	},
	"elements": [
		{
			"from": [3, 3, 1],
			"to": [10, 4, 4],
			"faces": {
				"north": {"uv": [3, 5, 10, 6], "texture": "#0"},
				"east": {"uv": [9, 4, 12, 5], "texture": "#0"},
				"south": {"uv": [5, 5, 12, 6], "texture": "#0"},
				"west": {"uv": [9, 4, 12, 5], "texture": "#0"},
				"up": {"uv": [5, 1, 12, 4], "texture": "#0"},
				"down": {"uv": [5, 1, 12, 4], "texture": "#0"}
			}
		},
		{
			"from": [7, 10, 1],
			"to": [12, 11, 2],
			"faces": {
				"north": {"uv": [3, 5, 8, 6], "texture": "#0"},
				"east": {"uv": [9, 4, 10, 5], "texture": "#0"},
				"south": {"uv": [5, 5, 10, 6], "texture": "#0"},
				"west": {"uv": [9, 4, 10, 5], "texture": "#0"},
				"up": {"uv": [5, 1, 10, 2], "texture": "#0"},
				"down": {"uv": [5, 1, 10, 2], "texture": "#0"}
			}
		},
		{
			"from": [4, 4, 1],
			"to": [9, 5, 2],
			"faces": {
				"north": {"uv": [3, 5, 8, 6], "texture": "#0"},
				"east": {"uv": [9, 4, 10, 5], "texture": "#0"},
				"south": {"uv": [5, 5, 10, 6], "texture": "#0"},
				"west": {"uv": [9, 4, 10, 5], "texture": "#0"},
				"up": {"uv": [5, 1, 10, 2], "texture": "#0"},
				"down": {"uv": [5, 1, 10, 2], "texture": "#0"}
			}
		},
		{
			"from": [4, 3, 4],
			"to": [9, 4, 5],
			"faces": {
				"north": {"uv": [3, 5, 8, 6], "texture": "#0"},
				"east": {"uv": [9, 4, 10, 5], "texture": "#0"},
				"south": {"uv": [5, 5, 10, 6], "texture": "#0"},
				"west": {"uv": [9, 4, 10, 5], "texture": "#0"},
				"up": {"uv": [5, 1, 10, 2], "texture": "#0"},
				"down": {"uv": [5, 1, 10, 2], "texture": "#0"}
			}
		},
		{
			"from": [5, 3, 0],
			"to": [8, 4, 1],
			"faces": {
				"north": {"uv": [3, 5, 6, 6], "texture": "#0"},
				"east": {"uv": [9, 4, 10, 5], "texture": "#0"},
				"south": {"uv": [5, 5, 8, 6], "texture": "#0"},
				"west": {"uv": [9, 4, 10, 5], "texture": "#0"},
				"up": {"uv": [5, 1, 8, 2], "texture": "#0"},
				"down": {"uv": [5, 1, 8, 2], "texture": "#0"}
			}
		},
		{
			"from": [9, 10, 0],
			"to": [10, 11, 1],
			"faces": {
				"north": {"uv": [3, 5, 4, 6], "texture": "#0"},
				"east": {"uv": [9, 4, 10, 5], "texture": "#0"},
				"south": {"uv": [5, 5, 6, 6], "texture": "#0"},
				"west": {"uv": [9, 4, 10, 5], "texture": "#0"},
				"up": {"uv": [5, 1, 6, 2], "texture": "#0"},
				"down": {"uv": [5, 1, 6, 2], "texture": "#0"}
			}
		},
		{
			"from": [5, 4, 2],
			"to": [8, 5, 3],
			"faces": {
				"north": {"uv": [3, 5, 6, 6], "texture": "#0"},
				"east": {"uv": [9, 4, 10, 5], "texture": "#0"},
				"south": {"uv": [5, 5, 8, 6], "texture": "#0"},
				"west": {"uv": [9, 4, 10, 5], "texture": "#0"},
				"up": {"uv": [5, 1, 8, 2], "texture": "#0"},
				"down": {"uv": [5, 1, 8, 2], "texture": "#0"}
			}
		},
		{
			"from": [8, 11, 1],
			"to": [11, 12, 2],
			"faces": {
				"north": {"uv": [3, 5, 6, 6], "texture": "#0"},
				"east": {"uv": [9, 4, 10, 5], "texture": "#0"},
				"south": {"uv": [5, 5, 8, 6], "texture": "#0"},
				"west": {"uv": [9, 4, 10, 5], "texture": "#0"},
				"up": {"uv": [5, 1, 8, 2], "texture": "#0"},
				"down": {"uv": [5, 1, 8, 2], "texture": "#0"}
			}
		},
		{
			"from": [8, 10, 2],
			"to": [11, 11, 3],
			"faces": {
				"north": {"uv": [3, 5, 6, 6], "texture": "#0"},
				"east": {"uv": [9, 4, 10, 5], "texture": "#0"},
				"south": {"uv": [5, 5, 8, 6], "texture": "#0"},
				"west": {"uv": [9, 4, 10, 5], "texture": "#0"},
				"up": {"uv": [5, 1, 8, 2], "texture": "#0"},
				"down": {"uv": [5, 1, 8, 2], "texture": "#0"}
			}
		}
	]
}