{
	"credit": "Made with Blockbench",
	"parent": "block/block",
	"textures": {
		"particle": "#all"
	},
	"elements": [
		{
			"from": [7, 0, 2],
			"to": [11, 1, 7],
			"faces": {
				"north": {"uv": [0, 0, 6, 1], "texture": "#all"},
				"east": {"uv": [0, 0, 5, 1], "texture": "#all"},
				"south": {"uv": [0, 0, 6, 1], "texture": "#all"},
				"west": {"uv": [0, 0, 5, 1], "texture": "#all"},
				"up": {"uv": [5, 6, 11, 11], "texture": "#all"},
				"down": {"uv": [0, 0, 6, 5], "texture": "#all"}
			}
		},
		{
			"from": [3, 0, 10],
			"to": [8, 1, 14],
			"faces": {
				"north": {"uv": [0, 0, 6, 1], "texture": "#all"},
				"east": {"uv": [0, 0, 5, 1], "texture": "#all"},
				"south": {"uv": [0, 0, 6, 1], "texture": "#all"},
				"west": {"uv": [0, 0, 5, 1], "texture": "#all"},
				"up": {"uv": [5, 6, 11, 11], "texture": "#all"},
				"down": {"uv": [0, 0, 6, 5], "texture": "#all"}
			}
		},
		{
			"from": [4, 0, 14],
			"to": [7, 1, 15],
			"faces": {
				"north": {"uv": [0, 0, 4, 1], "texture": "#all"},
				"east": {"uv": [0, 0, 2, 1], "texture": "#all"},
				"south": {"uv": [0, 0, 4, 1], "texture": "#all"},
				"west": {"uv": [0, 0, 2, 1], "texture": "#all"},
				"up": {"uv": [5, 4, 9, 6], "texture": "#all"},
				"down": {"uv": [0, 0, 4, 2], "texture": "#all"}
			}
		},
		{
			"from": [4, 0, 9],
			"to": [7, 1, 10],
			"faces": {
				"north": {"uv": [0, 0, 4, 1], "texture": "#all"},
				"east": {"uv": [0, 0, 2, 1], "texture": "#all"},
				"south": {"uv": [0, 0, 4, 1], "texture": "#all"},
				"west": {"uv": [0, 0, 2, 1], "texture": "#all"},
				"up": {"uv": [5, 4, 9, 6], "texture": "#all"},
				"down": {"uv": [0, 0, 4, 2], "texture": "#all"}
			}
		},
		{
			"from": [8, 0, 7],
			"to": [11, 1, 8],
			"faces": {
				"north": {"uv": [0, 0, 4, 1], "texture": "#all"},
				"east": {"uv": [0, 0, 2, 1], "texture": "#all"},
				"south": {"uv": [0, 0, 4, 1], "texture": "#all"},
				"west": {"uv": [0, 0, 2, 1], "texture": "#all"},
				"up": {"uv": [5, 4, 9, 6], "texture": "#all"},
				"down": {"uv": [0, 0, 4, 2], "texture": "#all"}
			}
		},
		{
			"from": [11, 0, 3],
			"to": [13, 1, 7],
			"faces": {
				"north": {"uv": [0, 0, 2, 1], "texture": "#all"},
				"east": {"uv": [0, 0, 2, 1], "texture": "#all"},
				"south": {"uv": [0, 0, 2, 1], "texture": "#all"},
				"west": {"uv": [0, 0, 2, 1], "texture": "#all"},
				"up": {"uv": [12, 2, 14, 4], "texture": "#all"},
				"down": {"uv": [0, 0, 2, 2], "texture": "#all"}
			}
		}
	]
}