{
  "type": "rankine:element",
  "name": "bismuth",
  "symbol": "Bi",
  "color": 14407127,
  "atomic": 83,
  "potential": 0.308,
  "items": ["T#forge:nuggets/bismuth","T#forge:ingots/bismuth","T#forge:storage_blocks/bismuth"],
  "values": [1,9,81],
  "durability": {
    "breaks": [100],
    "formulas": ["POWER"],
    "a": [1.15],
    "b": [0],
    "modifiers": ["NONE"],
    "limit": [0]
  },
  "miningspeed": {
    "breaks": [100],
    "formulas": ["LINEAR"],
    "a": [0.1],
    "b": [1],
    "modifiers": ["NONE"],
    "limit": [0]
  },
  "mininglevel": {
    "breaks": [5,9,100],
    "formulas": ["CONSTANT","CONSTANT","CONSTANT"],
    "a": [0,1,2],
    "b": [0,0,0],
    "modifiers": ["NONE","NONE","NONE"],
    "limit": [0,0,0]
  },
  "enchantability": {
    "breaks": [100],
    "formulas": ["LINEAR"],
    "a": [0.16667],
    "b": [0],
    "modifiers": ["NONE"],
    "limit": [0]
  },
  "corrosionresist": {
    "breaks": [100],
    "formulas": ["LINEAR"],
    "a": [0.008],
    "b": [0],
    "modifiers": ["MIN"],
    "limit": [1]
  }
}