{
  "type": "rankine:alloy_crafting",
  "group": "rankine:alloy_hammers",
  "inherit": true,
  "inheritRecipe": "rankine:alloying/nickel_superalloy_alloying",
  "key": {
    "#": {
      "item": "rankine:nickel_superalloy_ingot"
    },
    "s": {
      "alloyRecipe": "rankine:alloying/steel_alloying",
      "color": 3291714,
      "item": "rankine:alloy_rod",
      "langName": "item.rankine.steel_alloying"
    }
  },
  "pattern": [
    "###",
    "#s#",
    " s "
  ],
  "result": {
    "item": "rankine:nickel_superalloy_hammer"
  }
}