{
  "parent": "rankine:challenges/rankine_challenges",
  "display": {
    "icon": {
      "item": "rankine:skarn"
    },
    "title": {
      "translate": "rankine.advancements.challenges.rock_collector.title"
    },
    "description": {
      "translate": "rankine.advancements.challenges.rock_collector.description"
    },
    "frame": "challenge",
    "show_toast": true,
    "announce_to_chat": true,
    "hidden": false
  },
  "criteria": {
    "rankine:gray_granite": {
      "trigger": "minecraft:inventory_changed",
      "conditions": {
        "items": [
          {
            "item": "rankine:gray_granite"
          }
        ]
      }
    },
    "rankine:granodiorite": {
      "trigger": "minecraft:inventory_changed",
      "conditions": {
        "items": [
          {
            "item": "rankine:granodiorite"
          }
        ]
      }
    },
    "rankine:hornblende_andesite": {
      "trigger": "minecraft:inventory_changed",
      "conditions": {
        "items": [
          {
            "item": "rankine:hornblende_andesite"
          }
        ]
      }
    },
    "rankine:tholeiitic_basalt": {
      "trigger": "minecraft:inventory_changed",
      "conditions": {
        "items": [
          {
            "item": "rankine:tholeiitic_basalt"
          }
        ]
      }
    },
    "rankine:gabbro": {
      "trigger": "minecraft:inventory_changed",
      "conditions": {
        "items": [
          {
            "item": "rankine:gabbro"
          }
        ]
      }
    },
    "rankine:anorthosite": {
      "trigger": "minecraft:inventory_changed",
      "conditions": {
        "items": [
          {
            "item": "rankine:anorthosite"
          }
        ]
      }
    },
    "rankine:rhyolite": {
      "trigger": "minecraft:inventory_changed",
      "conditions": {
        "items": [
          {
            "item": "rankine:rhyolite"
          }
        ]
      }
    },
    "rankine:comendite": {
      "trigger": "minecraft:inventory_changed",
      "conditions": {
        "items": [
          {
            "item": "rankine:comendite"
          }
        ]
      }
    },
    "rankine:black_dacite": {
      "trigger": "minecraft:inventory_changed",
      "conditions": {
        "items": [
          {
            "item": "rankine:black_dacite"
          }
        ]
      }
    },
    "rankine:red_dacite": {
      "trigger": "minecraft:inventory_changed",
      "conditions": {
        "items": [
          {
            "item": "rankine:red_dacite"
          }
        ]
      }
    },
    "rankine:red_porphyry": {
      "trigger": "minecraft:inventory_changed",
      "conditions": {
        "items": [
          {
            "item": "rankine:red_porphyry"
          }
        ]
      }
    },
    "rankine:purple_porphyry": {
      "trigger": "minecraft:inventory_changed",
      "conditions": {
        "items": [
          {
            "item": "rankine:purple_porphyry"
          }
        ]
      }
    },
    "rankine:peridotite": {
      "trigger": "minecraft:inventory_changed",
      "conditions": {
        "items": [
          {
            "item": "rankine:peridotite"
          }
        ]
      }
    },
    "rankine:troctolite": {
      "trigger": "minecraft:inventory_changed",
      "conditions": {
        "items": [
          {
            "item": "rankine:troctolite"
          }
        ]
      }
    },
    "rankine:kimberlite": {
      "trigger": "minecraft:inventory_changed",
      "conditions": {
        "items": [
          {
            "item": "rankine:kimberlite"
          }
        ]
      }
    },
    "rankine:komatiite": {
      "trigger": "minecraft:inventory_changed",
      "conditions": {
        "items": [
          {
            "item": "rankine:komatiite"
          }
        ]
      }
    },
    "rankine:pumice": {
      "trigger": "minecraft:inventory_changed",
      "conditions": {
        "items": [
          {
            "item": "rankine:pumice"
          }
        ]
      }
    },
    "rankine:scoria": {
      "trigger": "minecraft:inventory_changed",
      "conditions": {
        "items": [
          {
            "item": "rankine:scoria"
          }
        ]
      }
    },
    "rankine:white_marble": {
      "trigger": "minecraft:inventory_changed",
      "conditions": {
        "items": [
          {
            "item": "rankine:white_marble"
          }
        ]
      }
    },
    "rankine:black_marble": {
      "trigger": "minecraft:inventory_changed",
      "conditions": {
        "items": [
          {
            "item": "rankine:black_marble"
          }
        ]
      }
    },
    "rankine:gneiss": {
      "trigger": "minecraft:inventory_changed",
      "conditions": {
        "items": [
          {
            "item": "rankine:gneiss"
          }
        ]
      }
    },
    "rankine:mica_schist": {
      "trigger": "minecraft:inventory_changed",
      "conditions": {
        "items": [
          {
            "item": "rankine:mica_schist"
          }
        ]
      }
    },
    "rankine:phyllite": {
      "trigger": "minecraft:inventory_changed",
      "conditions": {
        "items": [
          {
            "item": "rankine:phyllite"
          }
        ]
      }
    },
    "rankine:slate": {
      "trigger": "minecraft:inventory_changed",
      "conditions": {
        "items": [
          {
            "item": "rankine:slate"
          }
        ]
      }
    },
    "rankine:quartzite": {
      "trigger": "minecraft:inventory_changed",
      "conditions": {
        "items": [
          {
            "item": "rankine:quartzite"
          }
        ]
      }
    },
    "rankine:skarn": {
      "trigger": "minecraft:inventory_changed",
      "conditions": {
        "items": [
          {
            "item": "rankine:skarn"
          }
        ]
      }
    },
    "rankine:limestone": {
      "trigger": "minecraft:inventory_changed",
      "conditions": {
        "items": [
          {
            "item": "rankine:limestone"
          }
        ]
      }
    },
    "rankine:dolostone": {
      "trigger": "minecraft:inventory_changed",
      "conditions": {
        "items": [
          {
            "item": "rankine:dolostone"
          }
        ]
      }
    },
    "rankine:chalk": {
      "trigger": "minecraft:inventory_changed",
      "conditions": {
        "items": [
          {
            "item": "rankine:chalk"
          }
        ]
      }
    },
    "rankine:shale": {
      "trigger": "minecraft:inventory_changed",
      "conditions": {
        "items": [
          {
            "item": "rankine:shale"
          }
        ]
      }
    },
    "rankine:siltstone": {
      "trigger": "minecraft:inventory_changed",
      "conditions": {
        "items": [
          {
            "item": "rankine:siltstone"
          }
        ]
      }
    },
    "rankine:itacolumite": {
      "trigger": "minecraft:inventory_changed",
      "conditions": {
        "items": [
          {
            "item": "rankine:itacolumite"
          }
        ]
      }
    },
    "rankine:arkose": {
      "trigger": "minecraft:inventory_changed",
      "conditions": {
        "items": [
          {
            "item": "rankine:arkose"
          }
        ]
      }
    },
    "rankine:mudstone": {
      "trigger": "minecraft:inventory_changed",
      "conditions": {
        "items": [
          {
            "item": "rankine:mudstone"
          }
        ]
      }
    },
    "rankine:breccia": {
      "trigger": "minecraft:inventory_changed",
      "conditions": {
        "items": [
          {
            "item": "rankine:breccia"
          }
        ]
      }
    },
    "rankine:pegmatite": {
      "trigger": "minecraft:inventory_changed",
      "conditions": {
        "items": [
          {
            "item": "rankine:pegmatite"
          }
        ]
      }
    }
  },
  "requirements": [
    ["rankine:gray_granite"],
    ["rankine:granodiorite"],
    ["rankine:hornblende_andesite"],
    ["rankine:tholeiitic_basalt"],
    ["rankine:gabbro"],
    ["rankine:anorthosite"],
    ["rankine:rhyolite"],
    ["rankine:comendite"],
    ["rankine:black_dacite"],
    ["rankine:red_dacite"],
    ["rankine:red_porphyry"],
    ["rankine:purple_porphyry"],
    ["rankine:pegmatite"],
    ["rankine:peridotite"],
    ["rankine:troctolite"],
    ["rankine:kimberlite"],
    ["rankine:komatiite"],
    ["rankine:pumice"],
    ["rankine:scoria"],
    ["rankine:white_marble"],
    ["rankine:black_marble"],
    ["rankine:gneiss"],
    ["rankine:mica_schist"],
    ["rankine:phyllite"],
    ["rankine:slate"],
    ["rankine:quartzite"],
    ["rankine:skarn"],
    ["rankine:limestone"],
    ["rankine:dolostone"],
    ["rankine:chalk"],
    ["rankine:shale"],
    ["rankine:siltstone"],
    ["rankine:itacolumite"],
    ["rankine:arkose"],
    ["rankine:mudstone"],
    ["rankine:breccia"]
  ]
}