{
  "variants": {
    "facing=north,hanging=false": {
      "model": "rankine:block/sodium_vapor_lampwall"
    },
    "facing=south,hanging=false": {
      "model": "rankine:block/sodium_vapor_lampwall",
      "y": 180
    },
    "facing=west,hanging=false": {
      "model": "rankine:block/sodium_vapor_lampwall",
      "y": 270
    },
    "facing=east,hanging=false": {
      "model": "rankine:block/sodium_vapor_lampwall",
      "y": 90
    },
    "facing=north,hanging=true": {
      "model": "rankine:block/sodium_vapor_lamp"
    },
    "facing=south,hanging=true": {
      "model": "rankine:block/sodium_vapor_lamp",
      "y": 180
    },
    "facing=west,hanging=true": {
      "model": "rankine:block/sodium_vapor_lamp",
      "y": 270
    },
    "facing=east,hanging=true": {
      "model": "rankine:block/sodium_vapor_lamp",
      "y": 90
    }
  }
}