{
  "parent": "minecraft:recipes/root",
  "rewards": {
    "recipes": [
      "rankine:light_blue_cement_wall"
    ]
  },
  "criteria": {
    "has_light_blue_cement": {
      "trigger": "minecraft:inventory_changed",
      "conditions": {
        "items": [
          {
            "items": [
              "rankine:light_blue_cement"
            ]
          }
        ]
      }
    },
    "has_the_recipe": {
      "trigger": "minecraft:recipe_unlocked",
      "conditions": {
        "recipe": "rankine:light_blue_cement_wall"
      }
    }
  },
  "requirements": [
    [
      "has_light_blue_cement",
      "has_the_recipe"
    ]
  ]
}