{
  "type": "rankine:crushing",
  "input": {
    "item": "rankine:bauxite_ore"
  },
  "guaranteed": [
    {
      "item": "rankine:bauxite"
    }
  ],
  "outputs": [
    {
      "weight": 40,
      "remove": false
    },
    {
      "item": "rankine:kaolinite",
      "weight": 20,
      "remove": false
    },
    {
      "item": "rankine:fire_clay_ball",
      "weight": 20,
      "remove": false
    },
    {
      "item": "rankine:hematite",
      "weight": 5,
      "tier": "minecraft:iron"
    },
    {
      "item": "rankine:goethite",
      "weight": 5,
      "tier": "minecraft:iron"
    },
    {
      "item": "rankine:ilmenite",
      "weight": 5,
      "tier": "minecraft:diamond"
    },
    {
      "item": "rankine:rutile",
      "weight": 5,
      "tier": "minecraft:diamond"
    }
  ]
}