{
  "type": "rankine:crushing",
  "input": {
    "item": "rankine:porphyry_copper"
  },
  "output1": {
    "item": "rankine:copper_nugget",
    "count": 6,
    "chance": 1
  },
  "output2": {
    "item": "rankine:tellurium_nugget",
    "count": 6,
    "chance": 0.3,
    "additional": 0.15
  },
  "output3": {
    "item": "rankine:copper_nugget",
    "count": 6,
    "chance": 0.75,
    "additional": 0.15
  },
  "output4": {
    "item": "minecraft:selenium_nugget",
    "count": 6,
    "chance": 0.15,
    "additional": 0.1
  },
  "output5": {
    "item": "rankine:copper_nugget",
    "count": 6,
    "chance": 0.5,
    "additional": 0.2
  },
  "output6": {
    "item": "rankine:molybdenum_nugget",
    "count": 3,
    "chance": 0.1
  }
}