{
  "parent": "minecraft:recipes/root",
  "rewards": {
    "recipes": [
      "rankine:nitinol_ingot_from_nitinol_nugget"
    ]
  },
  "criteria": {
    "has_ingredient": {
      "trigger": "minecraft:inventory_changed",
      "conditions": {
        "items": [
          {
            "item": "rankine:nitinol_nugget"
          }
        ]
      }
    },
    "has_the_recipe": {
      "trigger": "minecraft:recipe_unlocked",
      "conditions": {
        "recipe": "rankine:nitinol_ingot_from_nitinol_nugget"
      }
    }
  },
  "requirements": [
    [
      "has_ingredient",
      "has_the_recipe"
    ]
  ]
}