{
  "parent": "minecraft:recipes/root",
  "rewards": {
    "recipes": [
      "minecraft:polished_black_dacite_stairs_from_polished_black_dacite__stonecutting"
    ]
  },
  "criteria": {
    "has_polished_black_dacite": {
      "trigger": "minecraft:inventory_changed",
      "conditions": {
        "items": [
          {
            "item": "rankine:polished_black_dacite"
          }
        ]
      }
    },
    "has_the_recipe": {
      "trigger": "minecraft:recipe_unlocked",
      "conditions": {
        "recipe": "minecraft:polished_black_dacite_stairs_from_polished_black_dacite__stonecutting"
      }
    }
  },
  "requirements": [
    [
      "has_polished_black_dacite",
      "has_the_recipe"
    ]
  ]
}