{
  "parent": "minecraft:recipes/root",
  "rewards": {
    "recipes": [
      "minecraft:polished_eclogite_wall_from_polished_eclogite__stonecutting"
    ]
  },
  "criteria": {
    "has_polished_eclogite": {
      "trigger": "minecraft:inventory_changed",
      "conditions": {
        "items": [
          {
            "item": "rankine:polished_eclogite"
          }
        ]
      }
    },
    "has_the_recipe": {
      "trigger": "minecraft:recipe_unlocked",
      "conditions": {
        "recipe": "minecraft:polished_eclogite_wall_from_polished_eclogite__stonecutting"
      }
    }
  },
  "requirements": [
    [
      "has_polished_eclogite",
      "has_the_recipe"
    ]
  ]
}