{
  "parent": "minecraft:recipes/root",
  "rewards": {
    "recipes": [
      "rankine:meteoric_iron_boots"
    ]
  },
  "criteria": {
    "has_alloy": {
      "trigger": "minecraft:inventory_changed",
      "conditions": {
        "items": [
          {
            "item": "rankine:meteoric_iron"
          }
        ]
      }
    },
    "has_the_recipe": {
      "trigger": "minecraft:recipe_unlocked",
      "conditions": {
        "recipe": "rankine:meteoric_iron_boots"
      }
    }
  },
  "requirements": [
    [
      "has_alloy",
      "has_the_recipe"
    ]
  ]
}