{
  "parent": "rankine:story/make_induction_furnace",
  "display": {
    "icon": {
      "item": "rankine:stainless_steel_pickaxe"
    },
    "title": {
      "translate": "rankine.advancements.story.make_stainless_steel.title"
    },
    "description": {
      "translate": "rankine.advancements.story.make_stainless_steel.description"
    },
    "frame": "challenge",
    "show_toast": true,
    "announce_to_chat": true,
    "hidden": false
  },
  "criteria": {
    "stainless_steel_pickaxe": {
      "trigger": "minecraft:inventory_changed",
      "conditions": {
        "items": [
          {
            "item": "rankine:stainless_steel_pickaxe"
          }
        ]
      }
    },
    "stainless_steel_axe": {
      "trigger": "minecraft:inventory_changed",
      "conditions": {
        "items": [
          {
            "item": "rankine:stainless_steel_axe"
          }
        ]
      }
    },
    "stainless_steel_sword": {
      "trigger": "minecraft:inventory_changed",
      "conditions": {
        "items": [
          {
            "item": "rankine:stainless_steel_sword"
          }
        ]
      }
    },
    "stainless_steel_hammer": {
      "trigger": "minecraft:inventory_changed",
      "conditions": {
        "items": [
          {
            "item": "rankine:stainless_steel_hammer"
          }
        ]
      }
    },
    "stainless_steel_shovel": {
      "trigger": "minecraft:inventory_changed",
      "conditions": {
        "items": [
          {
            "item": "rankine:stainless_steel_shovel"
          }
        ]
      }
    },
    "stainless_steel_spear": {
      "trigger": "minecraft:inventory_changed",
      "conditions": {
        "items": [
          {
            "item": "rankine:stainless_steel_spear"
          }
        ]
      }
    },
    "stainless_steel_hoe": {
      "trigger": "minecraft:inventory_changed",
      "conditions": {
        "items": [
          {
            "item": "rankine:stainless_steel_hoe"
          }
        ]
      }
    }
  },
  "requirements": [
    [
      "stainless_steel_pickaxe"
    ], [
      "stainless_steel_axe"
    ], [
      "stainless_steel_sword"
    ], [
      "stainless_steel_hammer"
    ], [
      "stainless_steel_shovel"
    ], [
      "stainless_steel_spear"
    ], [
      "stainless_steel_hoe"
    ]
  ]
}