{
  "name": "rankine.journal.cat_mineralogy.mineral_stones.name",
  "icon": "rankine:phosphorite",
  "category": "rankine:mineralogy",
  "pages": [
    {
      "type": "text",
      "text": "rankine.journal.cat_mineralogy.mineral_stones.text1"
    },
    {
      "type": "spotlight",
      "item": "rankine:phosphorite",
      "link_recipe": true,
      "text": "rankine.journal.cat_mineralogy.mineral_stones.phosphorite"
    },
    {
      "type": "spotlight",
      "item": "rankine:sylvinite",
      "link_recipe": true,
      "text": "rankine.journal.cat_mineralogy.mineral_stones.sylvinite"
    },
    {
      "type": "spotlight",
      "item": "rankine:banded_iron_formation",
      "link_recipe": true,
      "text": "rankine.journal.cat_mineralogy.mineral_stones.banded_iron_formation"
    },
    {
      "type": "spotlight",
      "item": "rankine:ironstone",
      "link_recipe": true,
      "text": "rankine.journal.cat_mineralogy.mineral_stones.ironstone"
    },
    {
      "type": "spotlight",
      "item": "rankine:bog_iron",
      "link_recipe": true,
      "text": "rankine.journal.cat_mineralogy.mineral_stones.bog_iron"
    }
  ]
}
